Control_Unit.v
module Control_Unit(instruction,RegDst,jump,Branch,MemRead,MemtoReg,ALUOP,MemWrite,ALUSrc,RegWrite);

input [5:0] instruction;
output reg RegDst;//falta probar 
output reg  jump;
output reg  Branch;
output reg  MemRead;
output reg  MemtoReg;
output reg  [5:0] ALUOP;
output reg MemWrite;
output reg ALUSrc;
output reg RegWrite;

always@(instruction)
begin
    if(instruction == 6'b000000) 
        begin
            RegDst<=1'b0;
            jump<=1'b0;
            Branch<=1'b0;
            MemRead<=1'b0;
            MemRead<=1'b0;
            MemtoReg<=1'b0;
            ALUOP<=instruction;
            MemWrite<=1'b0;
            ALUSrc<=1'b0;
            RegWrite<=1'b0;
        end
    else
        begin
            if( instruction == 6'b000001 || instruction== 6'b000111 || instruction==6'b000100 || instruction==6'b001010 )//operaciones normales como addi, subi y operaciones logicas  
                begin 
                    RegDst<=1'b1;
                    jump<=1'b0;
                    Branch<=1'b0;
                    MemRead<=1'b0;
                    MemRead<=1'b0;
                    MemtoReg<=1'b0;
                    ALUOP<=instruction;
                    MemWrite<=1'b0;
                    ALUSrc<=1'b1;
                    RegWrite<=1'b1;
                end  
            else if( instruction == 6'b000011 || instruction== 6'b000110 || instruction==6'b001001 )//operaciones de branch
                begin
                    RegDst<=1'b1;
                    jump<=1'b0;
                    Branch<=1'b1;
                    MemRead<=1'b0;
                    MemRead<=1'b0;
                    MemtoReg<=1'b0;
                    ALUOP<=instruction;
                    MemWrite<=1'b0;
                    ALUSrc<=1'b1;
                    RegWrite<=1'b1;            
                end
            
        //FALTA IMPLEMENTAR LOS ACCESOS DE MEMORIA SEAN LECTURA Y ESCRITURA.

        end
        //FALTA IMPLEMENTAR LOS JUMPS 
end


endmodule

Add_pc.v
module Add_pc(input [31:0] pc,output reg [31:0] pc_end);

always@(pc)
begin 
pc_end = pc + 4;
end

endmodule

Instruction_Memory.v
module Instruction_Memory(pc,out);
input [31:0] pc;
output reg [31:0] out;
reg [7:0] instrucciones [0:32];

initial begin 
    $readmemb("instructions.txt",instrucciones);
end

always@(pc)
begin 
    out <= {instrucciones[pc],instrucciones[pc+1],instrucciones[pc+2],instrucciones[pc+3]};
end


endmodule

Program_Counter.v
module Program_Counter(input clk,input reset,input [31:0] d,output reg [31:0] q);

always@(posedge clk,posedge reset)
if(reset==1'b1)
    q<=0;
else
    q<=d;
endmodule

Datapath.v
`include "Program_Counter.v"
`include "Instruction_Memory.v"
`include "Add_pc.v"
`include "Control_Unit.v"


module datapath();

reg clk;
reg reset;

//FETCH
//Signals(Instruction Memory and Program Counter)
wire [31:0] d;
wire [31:0] pc;
wire [31:0] instruction;

//Signals(Control Unit)
wire RegDst,jump,Branch,MemRead,MemtoReg,MemWrite,ALUSrc,RegWrite;
wire [5:0] ALUOP;



//FETCH
Program_Counter PC(.clk(clk),.reset(reset),.d(d),.q(pc));
Instruction_Memory IM(.pc(pc),.out(instruction));
Add_pc APC(.pc(pc),.pc_end(d));


//DECODE 
Control_Unit CU(.instruction(instruction[31:26]),.RegDst(RegDst),.jump(jump),.Branch(Branch),.MemRead(MemRead),.MemtoReg(MemtoReg),.ALUOP(ALUOP),.MemWrite(MemWrite),.ALUSrc(ALUSrc),.RegWrite(RegWrite));







always
begin
    #1clk=~clk;
end


initial begin
	$dumpfile("func.vcd");
	$dumpvars;
	$monitor(" pc = %b,%b,%d,%d,%d,%d",pc,instruction,RegDst,ALUOP,ALUSrc,RegWrite);
	reset<=1;
    clk<=1;
    #1;
    reset<=0;
	#13;$finish;

end

endmodule

func.vcd
$date
	Wed Mar 25 17:31:00 2020
$end
$version
	Icarus Verilog
$end
$timescale
	1s
$end
$scope module datapath $end
$var wire 32 ! pc [31:0] $end
$var wire 1 " jump $end
$var wire 32 # instruction [31:0] $end
$var wire 32 $ d [31:0] $end
$var wire 1 % RegWrite $end
$var wire 1 & RegDst $end
$var wire 1 ' MemtoReg $end
$var wire 1 ( MemWrite $end
$var wire 1 ) MemRead $end
$var wire 1 * Branch $end
$var wire 1 + ALUSrc $end
$var wire 6 , ALUOP [5:0] $end
$var reg 1 - clk $end
$var reg 1 . reset $end
$scope module APC $end
$var wire 32 / pc [31:0] $end
$var reg 32 0 pc_end [31:0] $end
$upscope $end
$scope module CU $end
$var wire 6 1 instruction [5:0] $end
$var reg 6 2 ALUOP [5:0] $end
$var reg 1 + ALUSrc $end
$var reg 1 * Branch $end
$var reg 1 ) MemRead $end
$var reg 1 ( MemWrite $end
$var reg 1 ' MemtoReg $end
$var reg 1 & RegDst $end
$var reg 1 % RegWrite $end
$var reg 1 " jump $end
$upscope $end
$scope module IM $end
$var wire 32 3 pc [31:0] $end
$var reg 32 4 out [31:0] $end
$upscope $end
$scope module PC $end
$var wire 1 - clk $end
$var wire 32 5 d [31:0] $end
$var wire 1 . reset $end
$var reg 32 6 q [31:0] $end
$upscope $end
$upscope $end
$enddefinitions $end
#0
$dumpvars
b0 6
b100 5
b100 4
b0 3
b0 2
b0 1
b100 0
b0 /
1.
1-
b0 ,
0+
0*
0)
0(
0'
0&
1%
b100 $
b100 #
0"
b0 !
$end
#1
0.
0-
#2
b1 #
b1 4
b1000 $
b1000 0
b1000 5
b100 !
b100 /
b100 3
b100 6
1-
#3
0-
#4
b100000 #
b100000 4
b1100 $
b1100 0
b1100 5
b1000 !
b1000 /
b1000 3
b1000 6
1-
#5
0-
#6
b1000 #
b1000 4
b10000 $
b10000 0
b10000 5
b1100 !
b1100 /
b1100 3
b1100 6
1-
#7
0-
#8
b1000000000000000000000010 #
b1000000000000000000000010 4
b10100 $
b10100 0
b10100 5
b10000 !
b10000 /
b10000 3
b10000 6
1-
#9
0-
#10
1+
b111 ,
b111 2
1&
b111 1
b11100000000000000000001000000 #
b11100000000000000000001000000 4
b11000 $
b11000 0
b11000 5
b10100 !
b10100 /
b10100 3
b10100 6
1-
#11
0-
#12
b1 ,
b1 2
b1 1
b100000000000000000000010000 #
b100000000000000000000010000 4
b11100 $
b11100 0
b11100 5
b11000 !
b11000 /
b11000 3
b11000 6
1-
#13
0-
#14
b100 ,
b100 2
b100 1
b10000000000000000000000000100 #
b10000000000000000000000000100 4
b100000 $
b100000 0
b100000 5
b11100 !
b11100 /
b11100 3
b11100 6
1-
